{
 "cells": [
  {
   "cell_type": "markdown",
   "metadata": {},
   "source": [
    "# Compilation vs. Interpretation\n",
    "\n",
    "## Compilation\n",
    "\n",
    "Source code in a language is translated, and maybe optimized, into code in another language, which is then executed.\n",
    "\n",
    "Examples: C, C++, Java\n",
    "\n",
    "## Interpretation\n",
    "\n",
    "Source code is directly executed by another program.\n",
    "\n",
    "Examples: Shell, JavaScript"
   ]
  },
  {
   "cell_type": "markdown",
   "metadata": {},
   "source": [
    "# Bytecode vs. Machine code\n",
    "\n",
    "Similarity: Both bytecode and machine code are produced by compiling source code.\n",
    "\n",
    "Differences:\n",
    "\n",
    "- Bytecode is either executable by software, or can be further transformed into machine code, which then is executable by hardware.\n",
    "- Machine code is executable by hardware.\n",
    "\n",
    "## Java bytecode\n",
    "\n",
    "Example bytecode instructions:\n",
    "\n",
    "- `iconst_0`: load the int value 0 onto the stack \n",
    "- `iconst_1`: load the int value 1 onto the stack\n",
    "- `istore`: store int value into variable #index \n",
    "- `istore_2`: store int value into variable 2\n",
    "- `istore_3`: store int value into variable 3\n",
    "- `iload_2`: load an int value from local variable 2\n",
    "- `iload_3`: load an int value from local variable 3\n",
    "- `iadd`: add two ints\n",
    "\n",
    "### Example\n",
    "\n",
    "The following Scala program can be compiled into Java bytecode.\n",
    "\n",
    "Scala program, which can be compiled via command `scalac HelloWorld.scala` into two files `HelloWorld.class` and `HelloWorld$.class`:\n",
    "\n",
    "```\n",
    "object HelloWorld {\n",
    "  def main(args: Array[String]): Unit = {\n",
    "    println(\"Hello, world!\")\n",
    "    val a = 0\n",
    "    val b = 1\n",
    "    val c = a + b\n",
    "  }\n",
    "}\n",
    "```\n",
    "\n",
    "Java bytecode, which is printed via command `javap -c HelloWorld\\$.class`:\n",
    "\n",
    "```\n",
    "Compiled from \"HelloWorld.scala\"\n",
    "public final class HelloWorld$ {\n",
    "  public static final HelloWorld$ MODULE$;\n",
    "\n",
    "  public static {};\n",
    "    Code:\n",
    "       0: new           #2                  // class HelloWorld$\n",
    "       3: dup\n",
    "       4: invokespecial #12                 // Method \"<init>\":()V\n",
    "       7: putstatic     #14                 // Field MODULE$:LHelloWorld$;\n",
    "      10: return\n",
    "\n",
    "  public void main(java.lang.String[]);\n",
    "    Code:\n",
    "       0: getstatic     #22                 // Field scala/Predef$.MODULE$:Lscala/Predef$;\n",
    "       3: ldc           #24                 // String Hello, world!\n",
    "       5: invokevirtual #28                 // Method scala/Predef$.println:(Ljava/lang/Object;)V\n",
    "       8: iconst_0\n",
    "       9: istore_2\n",
    "      10: iconst_1\n",
    "      11: istore_3\n",
    "      12: iload_2\n",
    "      13: iload_3\n",
    "      14: iadd\n",
    "      15: istore        4\n",
    "      17: return\n",
    "}\n",
    "```\n",
    "\n",
    "# References\n",
    "\n",
    "1. https://stackoverflow.com/questions/6889747/is-python-interpreted-or-compiled-or-both\n",
    "2. https://stackoverflow.com/questions/41570148/why-does-scala-place-a-dollar-sign-at-the-end-of-class-names\n",
    "3. https://en.wikipedia.org/wiki/Java_bytecode_instruction_listings"
   ]
  }
 ],
 "metadata": {
  "kernelspec": {
   "display_name": "Scala",
   "language": "scala",
   "name": "scala"
  },
  "language_info": {
   "codemirror_mode": "text/x-scala",
   "file_extension": ".sc",
   "mimetype": "text/x-scala",
   "name": "scala",
   "nbconvert_exporter": "script",
   "version": "2.13.3"
  }
 },
 "nbformat": 4,
 "nbformat_minor": 4
}
